auspost/__init__.py
auspost/py.typed
auspost-0.0.10.dist-info/WHEEL
auspost-0.0.10.dist-info/METADATA
auspost-0.0.10.dist-info/RECORD
